parse_formula/__init__.py
parse_formula/_parser.py
parse_formula/grammar.lark
parse_formula/py.typed
parse_formula-0.1.0.dist-info/WHEEL
parse_formula-0.1.0.dist-info/METADATA
parse_formula-0.1.0.dist-info/RECORD
