Metadata-Version: 2.4
Name: parse-formula
Version: 0.1.0
Summary: Chemical formula parser for Python
Author: Takumasa Nakamura
Author-email: Takumasa Nakamura <n.takumasa@gmail.com>
License-Expression: MIT
Classifier: Operating System :: OS Independent
Classifier: Programming Language :: Python
Classifier: Programming Language :: Python :: 3.8
Classifier: Programming Language :: Python :: 3.9
Classifier: Programming Language :: Python :: 3.10
Classifier: Programming Language :: Python :: 3.11
Classifier: Programming Language :: Python :: 3.12
Classifier: Programming Language :: Python :: 3.13
Classifier: Programming Language :: Python :: 3.14
Classifier: Programming Language :: Python :: Implementation :: CPython
Classifier: Topic :: Scientific/Engineering :: Chemistry
Classifier: Topic :: Scientific/Engineering :: Physics
Requires-Dist: importlib-resources>=5.0 ; python_full_version < '3.9'
Requires-Dist: lark>=1.3.1
Requires-Python: >=3.8
Project-URL: Source, https://github.com/n-takumasa/py-parse-formula
